runnem/__init__.py
runnem/cli.py
runnem/core.py
runnem-0.1.4.dist-info/licenses/LICENSE
runnem-0.1.4.dist-info/METADATA
runnem-0.1.4.dist-info/WHEEL
runnem-0.1.4.dist-info/entry_points.txt
runnem-0.1.4.dist-info/top_level.txt
runnem-0.1.4.dist-info/RECORD
