Metadata-Version: 2.4
Name: runnem
Version: 0.1.4
Summary: A service manager for managing multiple services in a project
Author-email: Daniel Murrell <dsmurrell@gmail.com>
License: MIT
Project-URL: Repository, https://github.com/dsmurrell/runnem.git
Classifier: Development Status :: 3 - Alpha
Classifier: Intended Audience :: Developers
Classifier: Programming Language :: Python :: 3
Classifier: Programming Language :: Python :: 3.8
Classifier: Programming Language :: Python :: 3.9
Classifier: Programming Language :: Python :: 3.10
Classifier: Programming Language :: Python :: 3.11
Requires-Python: >=3.8
License-File: LICENSE
Requires-Dist: pyyaml>=6.0
Requires-Dist: click>=8.0.0
Requires-Dist: requests>=2.31.0
Provides-Extra: test
Requires-Dist: pytest>=7.0.0; extra == "test"
Requires-Dist: pytest-cov>=4.0.0; extra == "test"
Requires-Dist: pytest-mock>=3.10.0; extra == "test"
Provides-Extra: dev
Requires-Dist: ruff>=0.4.2; extra == "dev"
Dynamic: license-file
